transervegeos/__init__.py
transervegeos/_transervegeos.py
transervegeos/_version.py
transervegeos-0.0.5.dist-info/LICENSE
transervegeos-0.0.5.dist-info/METADATA
transervegeos-0.0.5.dist-info/WHEEL
transervegeos-0.0.5.dist-info/top_level.txt
transervegeos-0.0.5.dist-info/RECORD
