Metadata-Version: 2.1
Name: transervegeos
Version: 0.0.5
Summary: A small example package
Author: Narayan Das Ahirwar
Author-email: ndahirwar93@gmail.com
Classifier: Programming Language :: Python :: 3
Classifier: License :: OSI Approved :: MIT License
Classifier: Operating System :: OS Independent
Requires-Python: >=3.8
License-File: LICENSE
Requires-Dist: geopandas
Requires-Dist: shapely
